priorityq/__init__.py
priorityq/core.py
priorityq/algorithms/__init__.py
priorityq/algorithms/dijkstra.py
priorityq/storage/__init__.py
priorityq/storage/base.py
priorityq/storage/binheap.py
priorityq/storage/binomialheap.py
priorityq/storage/listheap.py
priorityq-0.0.9.dist-info/DESCRIPTION.rst
priorityq-0.0.9.dist-info/METADATA
priorityq-0.0.9.dist-info/metadata.json
priorityq-0.0.9.dist-info/RECORD
priorityq-0.0.9.dist-info/top_level.txt
priorityq-0.0.9.dist-info/WHEEL
tests/__init__.py
tests/runtests.py
tests/test_core.py
tests/priorityq/__init__.py
tests/priorityq/core.py
tests/priorityq/algorithms/__init__.py
tests/priorityq/algorithms/dijkstra.py
tests/priorityq/storage/__init__.py
tests/priorityq/storage/base.py
tests/priorityq/storage/binheap.py
tests/priorityq/storage/binomialheap.py
tests/priorityq/storage/listheap.py
