Metadata-Version: 1.1
Name: priorityq
Version: 0.0.9
Summary: A flexible priority queue library with support for pluggable storage strategies and fast lookups and mutability.
Home-page: https://github.com/panyam/priorityq
Author: Sri Panyam
Author-email: sri.panyam@gmail.com
License: UNKNOWN
Keywords: priority queue,binary heap,heap,mutable heap,data structures
Platform: UNKNOWN
Classifier: Intended Audience :: Developers
Classifier: License :: OSI Approved :: MIT License
Classifier: Operating System :: OS Independent
